dbt/adapters/hive/.env
dbt/adapters/hive/__init__.py
dbt/adapters/hive/__version__.py
dbt/adapters/hive/cloudera_tracking.py
dbt/adapters/hive/column.py
dbt/adapters/hive/connections.py
dbt/adapters/hive/impl.py
dbt/adapters/hive/relation.py
dbt/include/hive/__init__.py
dbt/include/hive/dbt_project.yml
dbt/include/hive/sample_profiles.yml
dbt/include/hive/macros/adapters.sql
dbt/include/hive/macros/apply_grants.sql
dbt/include/hive/macros/materializations/seed.sql
dbt/include/hive/macros/materializations/snapshot.sql
dbt/include/hive/macros/materializations/table.sql
dbt/include/hive/macros/materializations/view.sql
dbt/include/hive/macros/materializations/incremental/incremental.sql
dbt/include/hive/macros/materializations/incremental/on_schema_change.sql
dbt/include/hive/macros/materializations/incremental/strategies.sql
dbt/include/hive/macros/materializations/incremental/validate.sql
dbt/include/hive/macros/utils/any_value.sql
dbt/include/hive/macros/utils/array_append.sql
dbt/include/hive/macros/utils/array_concat.sql
dbt/include/hive/macros/utils/array_construct.sql
dbt/include/hive/macros/utils/bool_or.sql
dbt/include/hive/macros/utils/cast_bool_to_text.sql
dbt/include/hive/macros/utils/concat.sql
dbt/include/hive/macros/utils/date_trunc.sql
dbt/include/hive/macros/utils/dateadd.sql
dbt/include/hive/macros/utils/datediff.sql
dbt/include/hive/macros/utils/escape_single_quotes.sql
dbt/include/hive/macros/utils/hash.sql
dbt/include/hive/macros/utils/last_day.sql
dbt/include/hive/macros/utils/listagg.sql
dbt/include/hive/macros/utils/position.sql
dbt/include/hive/macros/utils/right.sql
dbt/include/hive/macros/utils/split_part.sql
dbt/include/hive/macros/utils/timestamps.sql
dbt_hive-1.9.0.data/data/.env
dbt_hive-1.9.0.dist-info/LICENSE
dbt_hive-1.9.0.dist-info/METADATA
dbt_hive-1.9.0.dist-info/WHEEL
dbt_hive-1.9.0.dist-info/top_level.txt
dbt_hive-1.9.0.dist-info/RECORD
