Metadata-Version: 2.1
Name: dbt-hive
Version: 1.9.0
Summary: The Hive adapter plugin for dbt
Home-page: https://github.com/cloudera/dbt-hive
Author: Cloudera
Author-email: innovation-feedback@cloudera.com
License-File: LICENSE
Requires-Dist: dbt-core (~=1.9.0)
Requires-Dist: setuptools (>=40.3.0)
Requires-Dist: impyla (==0.18)
Requires-Dist: sqlparams (>=3.0.0)
Requires-Dist: python-decouple (>=3.6)
Requires-Dist: protobuf (<6,>=5.0.0)
Requires-Dist: kerberos (>=1.3.0) ; platform_system == "Darwin" or platform_system == "Linux"
Requires-Dist: winkerberos (>=0.9.1) ; platform_system == "Windows"
